README.rst
setup.cfg
setup.py
dnsknife/__init__.py
dnsknife/challenge.py
dnsknife/dnssec.py
dnsknife/exceptions.py
dnsknife/monkeypatch.py
dnsknife/openpgp.py
dnsknife/resolver.py
dnsknife/scanner.py
dnsknife/tpda.py
dnsknife.egg-info/PKG-INFO
dnsknife.egg-info/SOURCES.txt
dnsknife.egg-info/dependency_links.txt
dnsknife.egg-info/requires.txt
dnsknife.egg-info/top_level.txt
dnsknife/tests/__init__.py
dnsknife/tests/fake_dns.py
dnsknife/tests/test_cdscheck.py
dnsknife/tests/test_checker.py
dnsknife/tests/test_tpda.py