Metadata-Version: 2.1
Name: dnsknife
Version: 0.12
Summary: DNS tools
Home-page: https://github.com/gandi/dnsknife
Author: Gandi
Author-email: feedback@gandi.net
License: GPLv3
Keywords: dns lookup dnssec tpda rdap
Platform: UNKNOWN
Classifier: Development Status :: 3 - Alpha
Classifier: Programming Language :: Python
Classifier: Programming Language :: Python :: 2.6
Classifier: Programming Language :: Python :: 2.7
Classifier: Programming Language :: Python :: 3
Classifier: Programming Language :: Python :: 3.3
Classifier: Programming Language :: Python :: 3.4
Classifier: Topic :: Internet :: Name Service (DNS)
Classifier: Intended Audience :: Developers
Provides-Extra: socks
Provides-Extra: test
